{
  "project_info": {
    "project_number": "1049543524070",
    "project_id": "rewardrecycleapp-558a5",
    "storage_bucket": "rewardrecycleapp-558a5.firebasestorage.app"
  },
  "client": [
    {
      "client_info": {
        "mobilesdk_app_id": "1:1049543524070:android:78a2db02f7dab3eae30527",
        "android_client_info": {
          "package_name": "com.example.rewardrecycleapp"
        }
      },
      "oauth_client": [],
      "api_key": [
        {
          "current_key": "AIzaSyCIXV5Ud9fLNlM0UUgtJvluRLM8terKHxs"
        }
      ],
      "services": {
        "appinvite_service": {
          "other_platform_oauth_client": []
        }
      }
    }
  ],
  "configuration_version": "1"
}